fenics_ufl-2025.2.1.dist-info/licenses/COPYING
fenics_ufl-2025.2.1.dist-info/licenses/COPYING.LESSER
ufl/__init__.py
ufl/action.py
ufl/adjoint.py
ufl/algebra.py
ufl/argument.py
ufl/averaging.py
ufl/cell.py
ufl/checks.py
ufl/classes.py
ufl/coefficient.py
ufl/compound_expressions.py
ufl/conditional.py
ufl/constant.py
ufl/constantvalue.py
ufl/differentiation.py
ufl/domain.py
ufl/duals.py
ufl/equation.py
ufl/exprcontainers.py
ufl/exprequals.py
ufl/exproperators.py
ufl/finiteelement.py
ufl/form.py
ufl/formoperators.py
ufl/functionspace.py
ufl/geometry.py
ufl/index_combination_utils.py
ufl/indexed.py
ufl/indexsum.py
ufl/integral.py
ufl/integral_domain.py
ufl/mathfunctions.py
ufl/matrix.py
ufl/measure.py
ufl/objects.py
ufl/operators.py
ufl/permutation.py
ufl/precedence.py
ufl/protocols.py
ufl/pullback.py
ufl/py.typed
ufl/referencevalue.py
ufl/restriction.py
ufl/sobolevspace.py
ufl/sorting.py
ufl/split_functions.py
ufl/tensoralgebra.py
ufl/tensors.py
ufl/variable.py
ufl/algorithms/__init__.py
ufl/algorithms/ad.py
ufl/algorithms/analysis.py
ufl/algorithms/apply_algebra_lowering.py
ufl/algorithms/apply_coefficient_split.py
ufl/algorithms/apply_derivatives.py
ufl/algorithms/apply_function_pullbacks.py
ufl/algorithms/apply_geometry_lowering.py
ufl/algorithms/apply_integral_scaling.py
ufl/algorithms/apply_restrictions.py
ufl/algorithms/balancing.py
ufl/algorithms/change_to_reference.py
ufl/algorithms/check_arities.py
ufl/algorithms/check_restrictions.py
ufl/algorithms/checks.py
ufl/algorithms/comparison_checker.py
ufl/algorithms/compute_form_data.py
ufl/algorithms/coordinate_derivative_helpers.py
ufl/algorithms/domain_analysis.py
ufl/algorithms/estimate_degrees.py
ufl/algorithms/expand_indices.py
ufl/algorithms/formdata.py
ufl/algorithms/formfiles.py
ufl/algorithms/formsplitter.py
ufl/algorithms/formtransformations.py
ufl/algorithms/map_integrands.py
ufl/algorithms/remove_complex_nodes.py
ufl/algorithms/remove_component_tensors.py
ufl/algorithms/renumbering.py
ufl/algorithms/replace.py
ufl/algorithms/replace_derivative_nodes.py
ufl/algorithms/signature.py
fenics_ufl-2025.2.1.dist-info/METADATA
fenics_ufl-2025.2.1.dist-info/WHEEL
fenics_ufl-2025.2.1.dist-info/top_level.txt
fenics_ufl-2025.2.1.dist-info/RECORD
