Metadata-Version: 2.4
Name: fenics-ufl
Version: 2025.2.1
Summary: Unified Form Language
Author: UFL contributors
Maintainer: FEniCS Steering Council
Maintainer-email: fenics-steering-council@googlegroups.com
License-Expression: LGPL-3.0-or-later
Project-URL: homepage, https://fenicsproject.org
Project-URL: repository, https://github.com/fenics/ufl.git
Project-URL: documentation, https://docs.fenicsproject.org
Project-URL: issues, https://github.com/FEniCS/ufl/issues
Project-URL: funding, https://numfocus.org/donate
Requires-Python: >=3.10.0
License-File: COPYING
License-File: COPYING.LESSER
Requires-Dist: numpy
Provides-Extra: lint
Requires-Dist: mypy; extra == "lint"
Requires-Dist: ruff; extra == "lint"
Provides-Extra: typing
Requires-Dist: types-colorama; extra == "typing"
Provides-Extra: docs
Requires-Dist: sphinx; extra == "docs"
Requires-Dist: sphinx_rtd_theme; extra == "docs"
Provides-Extra: test
Requires-Dist: pytest; extra == "test"
Provides-Extra: ci
Requires-Dist: coveralls; extra == "ci"
Requires-Dist: coverage; extra == "ci"
Requires-Dist: pytest-cov; extra == "ci"
Requires-Dist: pytest-xdist; extra == "ci"
Requires-Dist: fenics-ufl[docs]; extra == "ci"
Requires-Dist: fenics-ufl[lint]; extra == "ci"
Requires-Dist: fenics-ufl[test]; extra == "ci"
Requires-Dist: fenics-ufl[typing]; extra == "ci"
Dynamic: license-file
